snudda/__init__.py
snudda/cli.py
snudda/convert_units.json
snudda/core.py
snudda/help.py
snudda/LFP/LFP.py
snudda/Parkinson/filter_flagser_data.py
snudda/Parkinson/filter_flagser_data_txt.py
snudda/Parkinson/init_wojtek.py
snudda/analyse/__init__.py
snudda/analyse/analyse.py
snudda/analyse/analyse_gap_junction_coupling.py
snudda/analyse/analyse_input.py
snudda/analyse/analyse_neuroinformatics2020.py
snudda/analyse/analyse_spike_trains.py
snudda/analyse/analyse_striatum.py
snudda/analyse/analyse_synapse_location.py
snudda/analyse/analyse_topology.py
snudda/analyse/analyse_topology_activity.py
snudda/analyse/spike_time_tiling_coefficient.py
snudda/data/InputAxons/Cortex/AA0059.swc
snudda/data/InputAxons/Cortex/Reg10/AA0059-reg10.swc
snudda/data/InputAxons/Cortex/Reg15/AA0059-reg15.swc
snudda/data/InputAxons/Cortex/Reg5/AA0059-reg5.swc
snudda/data/InputAxons/GPe2Striatum/example-projection-config.json
snudda/data/InputAxons/GPe2Striatum/prototypical-axon.swc
snudda/data/InputAxons/Thalamus/AA0054.swc
snudda/data/InputAxons/Thalamus/Reg10/AA0054-reg10.swc
snudda/data/InputAxons/Thalamus/Reg15/AA0054-reg15.swc
snudda/data/InputAxons/Thalamus/Reg5/AA0054-reg5.swc
snudda/data/density/1001_STRd_Sst_dens.csv
snudda/data/density/1001_STRd_Sst_dens_smooth.csv
snudda/data/density/252_STRd_Chat_dens.csv
snudda/data/density/252_STRd_Chat_dens_smooth.csv
snudda/data/density/352_STRd_Drd1_dens.csv
snudda/data/density/352_STRd_Drd1_dens_smooth.csv
snudda/data/density/72109410_STRd_Adora2a_dens.csv
snudda/data/density/72109410_STRd_Adora2a_dens_smooth.csv
snudda/data/density/79556738_STRd_Pvalb_dens.csv
snudda/data/density/79556738_STRd_Pvalb_dens_smooth.csv
snudda/data/density/combine_densities.py
snudda/data/density/dorsal_striatum_density.json
snudda/data/experiment_config/pair_recording/experiment-config-1.json
snudda/data/experiment_config/pair_recording/experiment-config-2.json
snudda/data/experiment_config/pair_recording/experiment-config-3.json
snudda-2.2.6.2.dist-info/licenses/LICENSE
snudda-2.2.6.2.dist-info/METADATA
snudda-2.2.6.2.dist-info/WHEEL
snudda-2.2.6.2.dist-info/entry_points.txt
snudda-2.2.6.2.dist-info/top_level.txt
snudda-2.2.6.2.dist-info/RECORD
