Metadata-Version: 2.4
Name: snudda
Version: 2.2.6.2
Summary: Create realistic networks of neurons, synapses placed using touch detection between axons and dendrites.
Author-email: Johannes Hjorth <hjorth@kth.se>
License: GPLv3
Classifier: Programming Language :: Python :: 3
Classifier: Operating System :: OS Independent
Requires-Python: >=3.11
License-File: LICENSE
Requires-Dist: bluepyopt>=1.14.18
Requires-Dist: h5py>=3.13
Requires-Dist: ipyparallel>=9.0.1
Requires-Dist: matplotlib>=3.9.4
Requires-Dist: mpi4py>=4.0.3
Requires-Dist: numpy>=2.2.3
Requires-Dist: scipy>=1.16.2
Requires-Dist: psutil>=7.0.0
Requires-Dist: numexpr>=2.10.2
Requires-Dist: numba>=0.60.0
Requires-Dist: wheel
Requires-Dist: vedo
Provides-Extra: dev
Requires-Dist: sphinx; extra == "dev"
Dynamic: license-file
